sopel_pronouns/__init__.py
sopel_pronouns/plugin.py
sopel_pronouns-0.1.0.dist-info/COPYING
sopel_pronouns-0.1.0.dist-info/METADATA
sopel_pronouns-0.1.0.dist-info/WHEEL
sopel_pronouns-0.1.0.dist-info/entry_points.txt
sopel_pronouns-0.1.0.dist-info/top_level.txt
sopel_pronouns-0.1.0.dist-info/RECORD
